_pbsim_internal/__init__.py
pybricks/hubs.py
pybricks/iodevices.py
pybricks/parameters.py
pybricks/pupdevices.py
pybricks/robotics.py
pybricks/tools.py
pbsim-0.1.2.dist-info/LICENSE.txt
pbsim-0.1.2.dist-info/METADATA
pbsim-0.1.2.dist-info/WHEEL
pbsim-0.1.2.dist-info/top_level.txt
pbsim-0.1.2.dist-info/RECORD
