Metadata-Version: 2.1
Name: pbsim
Version: 0.1.2
Summary: PyBricks SIMulator
License: GNU GENERAL PUBLIC LICENSE
Classifier: Development Status :: 1 - Planning
License-File: LICENSE.txt
